{
  "required": true,
  "minVersion": "0.8",
  "package": "org.ladysnake.impaled.mixin",
  "compatibilityLevel": "JAVA_17",
  "client": [
    "InGameHudMixin",
    "InGameOverlayRendererMixin",
    "impaling.EntityRendererMixin"
  ],
  "mixins": [
    "DamageSourcesMixin",
    "EfficiencyEnchantmentMixin",
    "EnchantmentTargetMixin",
    "EntityMixin",
    "LivingEntityMixin",
    "TridentEntityAccessor",
    "TridentRiptideFeatureRendererMixin",
    "impaling.ImpalingEnchantmentMixin",
    "impaling.MobEntityMixin",
    "impaling.PlayerEntityMixin",
    "impaling.TridentEntityMixin"
  ],
  "injectors": {
    "defaultRequire": 1
  }
}
